MANIFEST.in
README.md
setup.py
bin/linkbot-firmware-updater-cli.py
linkbot_firmware_updater/__init__.py
linkbot_firmware_updater/dialog.py
linkbot_firmware_updater/linkbot_firmware_updater.py
linkbot_firmware_updater/linkbot_firmware_updater_asyncmulti.py
linkbot_firmware_updater.egg-info/PKG-INFO
linkbot_firmware_updater.egg-info/SOURCES.txt
linkbot_firmware_updater.egg-info/dependency_links.txt
linkbot_firmware_updater.egg-info/entry_points.txt
linkbot_firmware_updater.egg-info/not-zip-safe
linkbot_firmware_updater.egg-info/requires.txt
linkbot_firmware_updater.egg-info/top_level.txt
linkbot_firmware_updater/hexfiles/v4.4.10.eeprom
linkbot_firmware_updater/hexfiles/v4.4.10.hex
linkbot_firmware_updater/hexfiles/v4.4.11.eeprom
linkbot_firmware_updater/hexfiles/v4.4.11.hex
linkbot_firmware_updater/hexfiles/v4.4.13.1.eeprom
linkbot_firmware_updater/hexfiles/v4.4.13.1.hex
linkbot_firmware_updater/hexfiles/v4.4.13.4.eeprom
linkbot_firmware_updater/hexfiles/v4.4.13.4.hex
linkbot_firmware_updater/hexfiles/v4.4.13.eeprom
linkbot_firmware_updater/hexfiles/v4.4.13.hex
linkbot_firmware_updater/hexfiles/v4.5.4.eeprom
linkbot_firmware_updater/hexfiles/v4.5.4.hex