Metadata-Version: 1.0
Name: linkbot-firmware-updater
Version: 0.1.6
Summary: Firmware Updating Tool for Barobo Linkbots.
Home-page: UNKNOWN
Author: David Ko
Author-email: david@barobo.com
License: UNKNOWN
Platform: UNKNOWN
